setup.py
tinytimer/__init__.py
tinytimer.egg-info/PKG-INFO
tinytimer.egg-info/SOURCES.txt
tinytimer.egg-info/dependency_links.txt
tinytimer.egg-info/top_level.txt