Metadata-Version: 1.1
Name: tinytimer
Version: 0.0.0
Summary: Tiny Python benchmarking library
Home-page: https://github.com/iskandr/microbench
Author: Alex Rubinsteyn
Author-email: alex {dot} rubinsteyn {at} gmail {dot} com
License: http://www.apache.org/licenses/LICENSE-2.0.html
Platform: UNKNOWN
Classifier: Development Status :: 3 - Alpha
Classifier: Environment :: Console
Classifier: Operating System :: OS Independent
Classifier: Intended Audience :: Science/Research
Classifier: License :: OSI Approved :: Apache Software License
Classifier: Programming Language :: Python
